gimme_secrets/__init__.py
gimme_secrets/cli.py
gimme_secrets/logging.py
gimme_secrets/aws/__init__.py
gimme_secrets/aws/decrypt_encrypt.py
gimme_secrets/aws/manage_secrets_parameterstore.py
gimme_secrets/aws/switch_account.py
gimme_secrets/azure/__init__.py
gimme_secrets/azure/decrypt_encrypt.py
gimme_secrets/azure/manage_secrets.py
gimme_secrets/core/__init__.py
gimme_secrets/core/validation.py
gimme_secrets/gcp/__init__.py
gimme_secrets/gcp/decrypt_encrypt.py
gimme_secrets-0.0.1.dev7.dist-info/LICENSE
gimme_secrets-0.0.1.dev7.dist-info/METADATA
gimme_secrets-0.0.1.dev7.dist-info/WHEEL
gimme_secrets-0.0.1.dev7.dist-info/entry_points.txt
gimme_secrets-0.0.1.dev7.dist-info/top_level.txt
gimme_secrets-0.0.1.dev7.dist-info/RECORD
