Metadata-Version: 2.1
Name: gimme-secrets
Version: 0.0.1.dev7
Summary: AWS Parameter Store management
Home-page: https://github.com/tomarv2/gimme-secrets
Author: Varun Tomar
Author-email: varuntomar2019@gmail.com
License: UNKNOWN
Platform: UNKNOWN
Classifier: Programming Language :: Python :: 3.6
Classifier: Operating System :: OS Independent
Requires-Python: >=3.6
Requires-Dist: click (==7.1.2)
Requires-Dist: tabulate (==0.8.7)
Requires-Dist: starlette
Requires-Dist: boto3
Requires-Dist: azure-common (==1.1.25)
Requires-Dist: azure-core (==1.5.0)
Requires-Dist: azure-identity (==1.3.1)
Requires-Dist: azure-keyvault (==4.0.0)
Requires-Dist: azure-keyvault-certificates (==4.2.0b1)
Requires-Dist: azure-keyvault-keys (==4.1.0)
Requires-Dist: azure-keyvault-secrets (==4.2.0b1)
Requires-Dist: google-cloud-kms
Requires-Dist: pytest
Requires-Dist: pytest-runner
Requires-Dist: moto
